{"name":"Lê Gia Tông","realName":"Lê Duy Cối Lê Duy Khoái","birth":"1661","lost":"1675 (13–14 tuổi) Đông Kinh, Đại Việt","position":"Hoàng đế Đại Việt","workTime":"1671 - 1675","era":"Nhà Lê trung hưng","father":"Lê Thần Tông","mother":"Lê Thị Ngọc Hoàn","preceded":"Lê Huyền Tông","succeeded":"Lê Hy Tông","alternameList":["Lê Gia Tông 黎嘉宗","Dương Đức (陽德: 1672 - 1674) Đức Nguyên (德元: 1674 - 1675)","Mỹ Hoàng đế","Gia Tông (嘉宗)"],"alternameString":"Lê Gia Tông 黎嘉宗, Dương Đức (陽德: 1672 - 1674) Đức Nguyên (德元: 1674 - 1675), Mỹ Hoàng đế, Gia Tông (嘉宗)."}