{"note":"số 1272/QĐ-TTg","historicSite":"Chiến trường Điện Biên Phủ","relatedFestival":"Chưa rõ","location":"Điện Biên Phủ","relatedThings":["Hồ Chí Minh","Võ Nguyên Giáp","Hoàng Văn Thái","Lê Liêm","Trần Đăng Ninh","Lê Trọng Tấn","Hoàng Minh Thảo","Lê Quảng Ba","Phạm Văn Đồng","Đặng Kim Giang","Lê Chưởng","Nguyễn Cận","Nguyễn Hải","Bùi Nam Hà","Trần Độ","Hoàng Kiện","Lê Thùy","Vũ Lập","Nguyễn Hữu An","Phạm Ngọc Mậu","Trần Văn Cẩn","Lê Đức Anh","Phan Đình Giót","Trần Can","Phạm Văn Phú","Nguyễn Sáng","Bùi Trang Chước","Lê Đức Thọ"],"approvedYear":"2009","describe":"là ","type":"Lịch sử đặc biệt"}