{"note":"đặc biệt 2009","historicSite":"Dinh Độc Lập","relatedFestival":"Chưa rõ","location":"và làm việc của Tổng thống Việt Nam Cộng hòa trước Sự kiện 30 tháng 4 năm 1975","relatedThings":["Ngô Viết Thụ","Ngô Đình Diệm","Nguyễn Văn Thiệu","Bùi Quang Thận","Vũ Đăng Toàn","Hồ Ba Bể","Hồ Hoàn Kiếm","Hồ Con Rùa"],"approvedYear":"1976","describe":"là một tòa dinh thự tại Thành phố Hồ Chí Minh, từng  nơi ở và m việc của Tổng thống Việt Nam Cộng hòa trước Sự kiện 30 tháng 4 năm 1975 di tích quốc gia đặc biệt","type":"Lịch sử kiến trúc đặc biệt"}