{"note":"Khu di tích lịch sử Kim Liên","historicSite":"Khu mộ bà Hoàng Thị Loan","relatedFestival":"Chưa rõ","location":"ng niệm chủ tịch Hồ Chí Minh tại xã Kim Liên, huyện Nam Đàn, tỉnh Nghệ An thuộc vùng duyên hải miền Trung Việt Nam, cách thành phố Vinh khoảng 15 km theo quốc lộ 46","relatedThings":["Hồ Chí Minh","Mai Hắc Đế","Nguyễn Sinh Sắc","Hồ Ba Bể","Hồ Hoàn Kiếm","Hồ Núi Cốc","Hồ Thác Bà","Hồ Hòa Bình","Hồ Tuyền Lâm","Lý Sơn","Hồ Lắk","Hồ Trị An","Phan Thiết"],"approvedYear":"","describe":"là khu di tích tưởng niệm chủ tịch Hồ Chí Minh tại xã Kim Liên, huyện Nam Đàn, tỉnh Nghệ An thuộc vùng duyên hải miền Trung Việt Nam, cách thành phố Vinh khoảng 15 km theo quốc lộ 46","type":"Lịch sử đặc biệt"}