{"note":"Không có","historicSite":"Núi Cánh Diều","relatedFestival":"Chưa rõ","location":"phía đông thành phố Ninh Bình, thuộc địa phận phường Thanh Bình trung tâm thành phố, trông núi có 3 đỉnh, đỉnh giữa cao, hai đỉnh tả hữu chĩa ra như cánh chim","relatedThings":["Cao Biền","Minh Mạng","Nguyễn Công Trứ","Lê Quý Đôn","Cao Bá Quát","Hồ Đồng Chương","Hồ Yên Thắng","Hồ Đồng Thái"],"approvedYear":"","describe":"là núi Cánh Diều,  di tích lịch sử văn hóa quốc gia nằm ở phía đông thành phố Ninh Bình, thuộc địa phận phường Thanh Bình","type":""}